ctypes_window_info/README.MD
ctypes_window_info/__init__.py
ctypes_window_info/requirements.txt
ctypes_window_info/thirdparty.json
ctypes_window_info-0.15.dist-info/LICENSE.rst
ctypes_window_info-0.15.dist-info/METADATA
ctypes_window_info-0.15.dist-info/WHEEL
ctypes_window_info-0.15.dist-info/top_level.txt
ctypes_window_info-0.15.dist-info/RECORD
