Metadata-Version: 2.1
Name: ctypes_window_info
Version: 0.15
Summary: Get window/process information with ctypes, no dependencies
Home-page: https://github.com/hansalemaos/ctypes_window_info
Author: Johannes Fischer
Author-email: aulasparticularesdealemaosp@gmail.com
License: MIT
Keywords: ctypes,windows,hwnd
Classifier: Development Status :: 4 - Beta
Classifier: Programming Language :: Python :: 3 :: Only
Classifier: Programming Language :: Python :: 3.10
Classifier: Topic :: Software Development :: Libraries :: Python Modules
Classifier: Topic :: Utilities
License-File: LICENSE.rst
